Metadata-Version: 2.1
Name: django-fastview
Version: 0.1.0
Summary: Build admin-style views with minimal code
Home-page: https://radiac.net/projects/django-fastview/
Author: Richard Terry
Author-email: code@radiac.net
License: BSD
Project-URL: Documentation, https://django-fastview.readthedocs.io/en/latest/
Project-URL: Source, https://github.com/radiac/django-fastview
Project-URL: Tracker, https://github.com/radiac/django-fastview/issues
Keywords: django crud admin
Platform: UNKNOWN
Classifier: Development Status :: 3 - Alpha
Classifier: Environment :: Web Environment
Classifier: Framework :: Django
Classifier: Framework :: Django :: 2.2
Classifier: Intended Audience :: Developers
Classifier: License :: OSI Approved :: BSD License
Classifier: Operating System :: OS Independent
Classifier: Programming Language :: Python
Classifier: Programming Language :: Python :: 3
Classifier: Programming Language :: Python :: 3 :: Only
Classifier: Programming Language :: Python :: 3.7
Classifier: Programming Language :: Python :: 3.8
Requires-Python: >=3.7
License-File: LICENSE
Requires-Dist: Django (>=2.2)
